{
  "runId": "QA-20260306-0052",
  "recordedAt": "2026-03-06T04:43:09.085Z",
  "recordedAtKst": "2026-03-06 13:43:09 KST",
  "runTitle": "Production Playwright MCP QA v8.7.9 - Guest PIN 4231 Full AI Flow",
  "owner": "codex",
  "source": "playwright-mcp",
  "environment": {
    "frontend": "Vercel",
    "backend": "Cloud Run",
    "branch": "main"
  },
  "checks": {
    "total": 9,
    "passed": 9,
    "failed": 0
  },
  "expertAssessments": [
    {
      "domainId": "ai-quality-assurance",
      "domainName": "AI Quality Assurance Specialist",
      "fit": "appropriate",
      "improvementNeeded": false,
      "rationale": "실환경에서 AI Chat, Reporter, Analyst 핵심 시나리오를 모두 검증했고 응답 품질과 렌더링이 안정적이었습니다.",
      "nextAction": ""
    },
    {
      "domainId": "ai-security-reliability",
      "domainName": "AI Security & Reliability Architect",
      "fit": "appropriate",
      "improvementNeeded": false,
      "rationale": "게스트 인증 게이트와 Health 응답, AI 기능 진입이 모두 정상이며 제공된 PIN 기반 접근 제어도 기대대로 동작했습니다.",
      "nextAction": ""
    },
    {
      "domainId": "test-automation",
      "domainName": "Test Automation Architect",
      "fit": "appropriate",
      "improvementNeeded": false,
      "rationale": "Playwright MCP로 인증부터 세 가지 AI 기능까지 사용자 경로를 실제 브라우저에서 검증했습니다.",
      "nextAction": ""
    }
  ],
  "completedImprovements": [
    {
      "id": "guest-login-pin-4231",
      "title": "게스트 PIN 4231 로그인 및 세션 진입",
      "priority": "P0",
      "isBlocking": true,
      "isBlockingExplicit": true,
      "overengineeringScope": "",
      "evidence": "제공된 PIN 4231로 로그인 성공 후 시스템 시작 카운트다운을 거쳐 /dashboard 진입",
      "note": "",
      "owner": "",
      "status": "completed",
      "policyNote": ""
    },
    {
      "id": "dashboard-health-v879",
      "title": "프로덕션 대시보드 및 Health API 검증",
      "priority": "P0",
      "isBlocking": true,
      "isBlockingExplicit": true,
      "overengineeringScope": "",
      "evidence": "Dashboard 렌더링 정상, /api/health 200 healthy, version 8.7.9, database/cache/ai connected",
      "note": "",
      "owner": "",
      "status": "completed",
      "policyNote": ""
    },
    {
      "id": "ai-chat-response-quality-v879",
      "title": "AI Chat 스트리밍 응답 및 권고 검증",
      "priority": "P0",
      "isBlocking": true,
      "isBlockingExplicit": true,
      "overengineeringScope": "",
      "evidence": "Cloud Run AI 응답 생성 성공, 15대 서버 요약과 cache-redis-dc1-01 메모리 권고 포함",
      "note": "",
      "owner": "",
      "status": "completed",
      "policyNote": ""
    },
    {
      "id": "reporter-generate-detail-v879",
      "title": "Reporter 보고서 생성 및 상세보기",
      "priority": "P0",
      "isBlocking": true,
      "isBlockingExplicit": true,
      "overengineeringScope": "",
      "evidence": "자동장애 보고서 생성 성공, 감지된 이상 항목/권장 조치/감지 패턴 렌더링 확인",
      "note": "",
      "owner": "",
      "status": "completed",
      "policyNote": ""
    },
    {
      "id": "analyst-full-analysis-v879",
      "title": "Analyst 전체 분석 및 드릴다운",
      "priority": "P0",
      "isBlocking": true,
      "isBlockingExplicit": true,
      "overengineeringScope": "",
      "evidence": "15개 서버 전체 분석 성공, cache-redis-dc1-01 메모리 82%→97% 상승 예측과 상세 인사이트 확인",
      "note": "",
      "owner": "",
      "status": "completed",
      "policyNote": ""
    }
  ],
  "pendingImprovements": [],
  "deferredImprovements": [],
  "wontFixImprovements": [],
  "notes": [
    "QA-1: Landing Page - PASS (v8.7.9 랜딩 렌더링 및 로그인 유도 CTA 확인)",
    "QA-2: Login Gate - PASS (로그인 필요 모달과 /login 진입 정상)",
    "QA-3: Guest Login - PASS (PIN 4231 성공, 게스트 사용자/게스트 모드 상태 표시)",
    "QA-4: System Boot - PASS (시스템 시작 카운트다운 후 /system-boot 경유, /dashboard 진입)",
    "QA-5: Dashboard - PASS (전체 15, 온라인 14, 경고 1, 위험 0, 오프라인 0)",
    "QA-6: Health API - PASS (200 healthy, version 8.7.9, database/cache/ai connected)",
    "QA-7: AI Chat - PASS (~8초, 스트리밍 진행 표시 후 서버 요약/권고 응답)",
    "QA-8: Reporter - PASS (~3초, 보고서 생성 및 상세보기 렌더링)",
    "QA-9: Analyst - PASS (~12초, 전체 분석 결과와 cache-redis-dc1-01 드릴다운 확인)",
    "브라우저 콘솔의 403 1건은 초기 오입력 PIN 테스트에서 발생한 /api/auth/guest-login 응답으로, 최종 성공 시나리오의 결함은 아니었습니다."
  ],
  "links": [
    {
      "label": "Vercel Production",
      "url": "https://openmanager-ai.vercel.app"
    },
    {
      "label": "Validated Deployment",
      "url": "https://openmanager-d4uu8g7dg-skyasus-projects.vercel.app"
    }
  ]
}
